nuvpy/__init__.py
nuvpy/nuviot_auth.py
nuvpy/nuviot_data.py
nuvpy/nuviot_device.py
nuvpy/nuviot_email.py
nuvpy/nuviot_jobs.py
nuvpy/nuviot_report_builder.py
nuvpy/nuviot_srvc.py
nuvpy/nuviot_util.py
nuvpy-1.4.12.dist-info/License.txt
nuvpy-1.4.12.dist-info/METADATA
nuvpy-1.4.12.dist-info/WHEEL
nuvpy-1.4.12.dist-info/top_level.txt
nuvpy-1.4.12.dist-info/RECORD
