Metadata-Version: 2.1
Name: nuvpy
Version: 1.4.12
Summary: Python libraries for access to data generated from IoT devices captured with NuvIoT
Home-page: https://github.com/lagovista/nuvpy
Download-URL: https://github.com/lagovista/nuvpy/archive/v_1.4.12.tar.gz
Author: Software Logistics, LLC
Author-email: kevinw@software-logistics.com
License: MIT
Keywords: NuvIoT,IoT,Devices,Machine Learning
Classifier: Programming Language :: Python :: 3
Classifier: License :: OSI Approved :: MIT License
Classifier: Operating System :: OS Independent
Requires-Python: >=3.6
License-File: License.txt
Requires-Dist: jsonschema
Requires-Dist: urllib3
Requires-Dist: requests
Requires-Dist: tqdm
Requires-Dist: tzdata
Requires-Dist: fpdf
Requires-Dist: sendgrid
Requires-Dist: certifi
Requires-Dist: chardet
Requires-Dist: pandas
Requires-Dist: sqlalchemy
